ktune/__init__.py
ktune/requirements.txt
ktune/cli/__init__.py
ktune/cli/__main__.py
ktune/cli/command.py
ktune/config/__init__.py
ktune/config/validation.py
ktune/core/__init__.py
ktune/core/tune.py
ktune/core/sysid/__init__.py
ktune/core/sysid/testbed/__init__.py
ktune/core/sysid/testbed/base.py
ktune/core/sysid/testbed/pendulum.py
ktune/core/utils/__init__.py
ktune/core/utils/datalog.py
ktune/core/utils/filters.py
ktune/core/utils/metrics.py
ktune/core/utils/plots.py
ktune-0.2.4.dist-info/licenses/LICENSE
ktune-0.2.4.dist-info/METADATA
ktune-0.2.4.dist-info/WHEEL
ktune-0.2.4.dist-info/entry_points.txt
ktune-0.2.4.dist-info/top_level.txt
ktune-0.2.4.dist-info/RECORD
