Metadata-Version: 2.4
Name: ktune
Version: 0.2.4
Summary: Servo Control Tuning Tool for Real and Simulated Actuators. Utilizes Kscale KOS and KOS-SIM
Home-page: https://github.com/nfreq/ktune
Author: Scott
Author-email: scott@whoopnet.ai
Classifier: Development Status :: 3 - Alpha
Classifier: Intended Audience :: Developers
Classifier: License :: OSI Approved :: MIT License
Classifier: Operating System :: OS Independent
Classifier: Programming Language :: Python :: 3
Classifier: Programming Language :: Python :: 3.11
Classifier: Topic :: Software Development :: Libraries :: Python Modules
Requires-Python: >=3.11
License-File: LICENSE
Requires-Dist: numpy>=1.20.0
Requires-Dist: matplotlib>=3.0.0
Requires-Dist: pykos
Requires-Dist: jsonschema
Provides-Extra: dev
Requires-Dist: pytest>=7.0.0; extra == "dev"
Requires-Dist: black>=22.0.0; extra == "dev"
Requires-Dist: mypy>=1.0.0; extra == "dev"
Requires-Dist: ruff>=0.1.0; extra == "dev"
Provides-Extra: examples
Requires-Dist: matplotlib>=3.0.0; extra == "examples"
Requires-Dist: numpy>=1.20.0; extra == "examples"
Dynamic: author
Dynamic: author-email
Dynamic: classifier
Dynamic: description
Dynamic: description-content-type
Dynamic: home-page
Dynamic: license-file
Dynamic: provides-extra
Dynamic: requires-dist
Dynamic: requires-python
Dynamic: summary
